netx_fdl_compiler/FDLSchema.json
netx_fdl_compiler/__init__.py
netx_fdl_compiler/__main__.py
netx_fdl_compiler/fdlconverter.py
netx_fdl_compiler-0.1.3.dist-info/LICENSE
netx_fdl_compiler-0.1.3.dist-info/METADATA
netx_fdl_compiler-0.1.3.dist-info/WHEEL
netx_fdl_compiler-0.1.3.dist-info/top_level.txt
netx_fdl_compiler-0.1.3.dist-info/RECORD
