Metadata-Version: 2.1
Name: netx-fdl-compiler
Version: 0.1.3
Summary: Flash device label compiler for Hilscher netX90
Home-page: https://github.com/pfox89/netx_fdl_compiler.git
Author: Paul Fox
Author-email: paul.fox@temposonics.com
License: UNKNOWN
Platform: UNKNOWN
Classifier: Programming Language :: Python :: 3.7
Classifier: Operating System :: OS Independent
Classifier: Topic :: Software Development :: Embedded Systems
Classifier: License :: OSI Approved :: Apache Software License
Requires-Python: >=3.7
License-File: LICENSE
Requires-Dist: construct
Requires-Dist: pyyaml
